setup.py
yamunaque_examples/__init__.py
yamunaque_examples/example_1.py
yamunaque_examples/example_2.py
yamunaque_examples.egg-info/PKG-INFO
yamunaque_examples.egg-info/SOURCES.txt
yamunaque_examples.egg-info/dependency_links.txt
yamunaque_examples.egg-info/not-zip-safe
yamunaque_examples.egg-info/top_level.txt