Metadata-Version: 1.0
Name: yamunaque-examples
Version: 1.0
Summary: Package example
Home-page: UNKNOWN
Author: Denis Yamunaque
Author-email: dy.xcvi@gmail.com
License: UNKNOWN
Platform: UNKNOWN
